tests/__init__.py
tests/tests.py
threshold_optimizer/__init__.py
threshold_optimizer/threshold_optimizer.py
threshold_optimizer-0.0.1a2.dist-info/LICENSE
threshold_optimizer-0.0.1a2.dist-info/METADATA
threshold_optimizer-0.0.1a2.dist-info/WHEEL
threshold_optimizer-0.0.1a2.dist-info/top_level.txt
threshold_optimizer-0.0.1a2.dist-info/RECORD
