Metadata-Version: 2.1
Name: threshold-optimizer
Version: 0.0.1a2
Summary: Optimize decision boundary/threshold for predicted probabilities from binary classification
Home-page: https://github.com/pyparakeets/budgies
Author: Mawuli Adjei, Adu Boahene, Tobelum Eze Okoli, Wayne Yu
Author-email: pyparakeets@gmail.com
License: MIT
Project-URL: Source, https://github.com/pyparakeets/budgies
Project-URL: Tracker, https://github.com/pyparakeets/budgies/issues
Keywords: Optimize Decision Boundary Threshold Binary Classification Probabilities
Platform: UNKNOWN
Classifier: Development Status :: 3 - Alpha
Classifier: Intended Audience :: Science/Research
Classifier: Topic :: Scientific/Engineering :: Artificial Intelligence
Classifier: License :: OSI Approved :: MIT License
Classifier: Programming Language :: Python :: 3
Classifier: Programming Language :: Python :: 3.7
Requires-Python: >=3.6
Requires-Dist: scikit-learn (==0.24.0)
Requires-Dist: pandas (==0.25.1)
Requires-Dist: numpy (==1.17.1)
